.DS_Store
pneumatic/__init__.py
pneumatic/db.py
pneumatic/excludes.py
pneumatic/uploader.py
pneumatic/utils.py
pneumatic-0.1.9.dist-info/AUTHORS.rst
pneumatic-0.1.9.dist-info/LICENSE
pneumatic-0.1.9.dist-info/METADATA
pneumatic-0.1.9.dist-info/WHEEL
pneumatic-0.1.9.dist-info/top_level.txt
pneumatic-0.1.9.dist-info/RECORD
