Metadata-Version: 2.1
Name: pneumatic
Version: 0.1.9
Summary: A bulk upload library for DocumentCloud.
Home-page: http://pneumatic.readthedocs.io/en/latest/
Author: Anthony DeBarros
Author-email: practicalsqlbook@gmail.com
License: MIT
Platform: UNKNOWN
Classifier: Development Status :: 4 - Beta
Classifier: Intended Audience :: Developers
Classifier: License :: OSI Approved :: MIT License
Classifier: Natural Language :: English
Classifier: Operating System :: OS Independent
Classifier: Programming Language :: Python :: 3
Classifier: Programming Language :: Python :: 3.5
Classifier: Programming Language :: Python :: 3.6
Classifier: Programming Language :: Python :: 3.7
Classifier: Programming Language :: Python :: 3.8
Requires-Dist: requests
Requires-Dist: colorama
